fd_hash/__init__.py
fd_hash/main.py
fd_hash-0.0.3.dist-info/METADATA
fd_hash-0.0.3.dist-info/WHEEL
fd_hash-0.0.3.dist-info/entry_points.txt
fd_hash-0.0.3.dist-info/top_level.txt
fd_hash-0.0.3.dist-info/RECORD
