Metadata-Version: 2.1
Name: fd-hash
Version: 0.0.3
Summary: Simple utility to track folder content by generating hash descriptions
Home-page: https://github.com/xirenhua/fd_hash
Author: xirenhua
Author-email: xirenhua@outlook.com
License: UNKNOWN
Platform: UNKNOWN
Requires-Dist: click
